bulk_directory_tree.py
bulk_directory_tree-1.0.8.dist-info/LICENSE
bulk_directory_tree-1.0.8.dist-info/METADATA
bulk_directory_tree-1.0.8.dist-info/WHEEL
bulk_directory_tree-1.0.8.dist-info/entry_points.txt
bulk_directory_tree-1.0.8.dist-info/top_level.txt
bulk_directory_tree-1.0.8.dist-info/RECORD
