Metadata-Version: 2.1
Name: bulk_directory_tree
Version: 1.0.8
Summary: Create n node d depth bulk directory tree in any directory
Home-page: https://github.com/saumiko/bulk-directory-tree
Author: Asif Mohaimen
Author-email: saumik01@gmail.com
Classifier: Programming Language :: Python :: 3
Classifier: Operating System :: OS Independent
Requires-Python: >=2.6, !=3.0.*, !=3.1.*, !=3.2.*, <4
License-File: LICENSE
Requires-Dist: Click ==8.1.7
